odoo/addons/account_bank_statement_import_online_ua_pb_interpay/README.rst
odoo/addons/account_bank_statement_import_online_ua_pb_interpay/__init__.py
odoo/addons/account_bank_statement_import_online_ua_pb_interpay/__manifest__.py
odoo/addons/account_bank_statement_import_online_ua_pb_interpay/i18n/account_bank_statement_import_online_ua_pb_interpay.pot
odoo/addons/account_bank_statement_import_online_ua_pb_interpay/models/__init__.py
odoo/addons/account_bank_statement_import_online_ua_pb_interpay/models/online_bank_statement_provider_ua_pb_interpay.py
odoo/addons/account_bank_statement_import_online_ua_pb_interpay/readme/CONFIGURE.rst
odoo/addons/account_bank_statement_import_online_ua_pb_interpay/readme/CONTRIBUTORS.rst
odoo/addons/account_bank_statement_import_online_ua_pb_interpay/readme/DESCRIPTION.rst
odoo/addons/account_bank_statement_import_online_ua_pb_interpay/readme/ROADMAP.rst
odoo/addons/account_bank_statement_import_online_ua_pb_interpay/readme/USAGE.rst
odoo/addons/account_bank_statement_import_online_ua_pb_interpay/static/description/icon.png
odoo/addons/account_bank_statement_import_online_ua_pb_interpay/static/description/index.html
odoo/addons/account_bank_statement_import_online_ua_pb_interpay/tests/__init__.py
odoo/addons/account_bank_statement_import_online_ua_pb_interpay/tests/test_account_bank_statement_import_online_ua_pb_interpay.py
odoo/addons/account_bank_statement_import_online_ua_pb_interpay/views/online_bank_statement_provider.xml
odoo12_addon_account_bank_statement_import_online_ua_pb_interpay-12.0.1.1.0.dist-info/METADATA
odoo12_addon_account_bank_statement_import_online_ua_pb_interpay-12.0.1.1.0.dist-info/WHEEL
odoo12_addon_account_bank_statement_import_online_ua_pb_interpay-12.0.1.1.0.dist-info/top_level.txt
odoo12_addon_account_bank_statement_import_online_ua_pb_interpay-12.0.1.1.0.dist-info/RECORD
