Metadata-Version: 2.1
Name: odoo12-addon-account-bank-statement-import-online-ua-pb-interpay
Version: 12.0.1.1.0
Summary: Online bank statements for InterPay.PrivatBank.ua
Home-page: https://github.com/OCA/l10n-ukraine/
Author: CorporateHub, Odoo Community Association (OCA)
Author-email: support@odoo-community.org
License: AGPL-3
Platform: UNKNOWN
Classifier: Programming Language :: Python
Classifier: Framework :: Odoo
Classifier: License :: OSI Approved :: GNU Affero General Public License v3
Requires-Python: >=3.5
Requires-Dist: odoo12-addon-account-bank-statement-import-online
Requires-Dist: odoo (<12.1dev,>=12.0a)
